lazypredict/Supervised.py
lazypredict/__init__.py
lazypredict/cli.py
lazypredict-0.2.15.dist-info/licenses/AUTHORS.md
lazypredict-0.2.15.dist-info/licenses/LICENSE
lazypredict-0.2.15.dist-info/METADATA
lazypredict-0.2.15.dist-info/WHEEL
lazypredict-0.2.15.dist-info/entry_points.txt
lazypredict-0.2.15.dist-info/top_level.txt
lazypredict-0.2.15.dist-info/RECORD
