Metadata-Version: 2.4
Name: lazypredict
Version: 0.2.15
Summary: Lazy Predict help build a lot of basic models without much code and helps understand which models works better without any parameter tuning
Home-page: https://github.com/shankarpandala/lazypredict
Author: Shankar Rao Pandala
Author-email: shankar.pandala@live.com
License: MIT license
Keywords: lazypredict
Classifier: Development Status :: 3 - Alpha
Classifier: Intended Audience :: Developers
Classifier: License :: OSI Approved :: MIT License
Classifier: Natural Language :: English
Classifier: Programming Language :: Python :: 3.8
Classifier: Programming Language :: Python :: 3.9
Classifier: Programming Language :: Python :: 3.10
Classifier: Programming Language :: Python :: 3.11
Classifier: Programming Language :: Python :: 3.12
Classifier: Programming Language :: Python :: 3.13
Requires-Python: >=3.8
License-File: LICENSE
License-File: AUTHORS.md
Requires-Dist: click
Requires-Dist: scikit-learn
Requires-Dist: pandas
Requires-Dist: tqdm
Requires-Dist: joblib
Requires-Dist: lightgbm
Requires-Dist: xgboost
Requires-Dist: pytest-runner
Requires-Dist: mlflow>=2.0.0
Dynamic: author
Dynamic: author-email
Dynamic: classifier
Dynamic: description
Dynamic: description-content-type
Dynamic: home-page
Dynamic: keywords
Dynamic: license
Dynamic: license-file
Dynamic: requires-dist
Dynamic: requires-python
Dynamic: summary
